{
  "condition": "baseline",
  "seed": 6,
  "n_train": 1000,
  "init_scale": 8.0,
  "loss": "mse",
  "opt": "adamw",
  "lr": 0.001,
  "wd": 0.01,
  "steps": 100000,
  "batch_size": 200,
  "lambda_con": 0.3,
  "tau": 0.1,
  "proj_dim": 64,
  "max_shift": 3,
  "norm_clamp": 60.0,
  "eval_every": 200,
  "t_gen_acc": 0.85,
  "out_dir": "E:\\GitHub\\Research\\mem-gen-delay\\runs\\grid5r3\\base_clamp60_s6",
  "t_fit": 600,
  "t_gen": 19600,
  "steps_ran": 29601,
  "nn_purity": null,
  "wall_seconds": 74.6
}